apprise/__init__.py
apprise/apprise.py
apprise/apprise_attachment.py
apprise/apprise_config.py
apprise/asset.py
apprise/cli.py
apprise/common.py
apprise/conversion.py
apprise/emojis.py
apprise/exception.py
apprise/locale.py
apprise/logger.py
apprise/manager.py
apprise/manager_attachment.py
apprise/manager_config.py
apprise/manager_plugins.py
apprise/persistent_store.py
apprise/py.typed
apprise/url.py
apprise/assets/NotifyXML-1.0.xsd
apprise/assets/NotifyXML-1.1.xsd
apprise/assets/themes/default/apprise-failure-128x128.ico
apprise/assets/themes/default/apprise-failure-128x128.png
apprise/assets/themes/default/apprise-failure-256x256.png
apprise/assets/themes/default/apprise-failure-32x32.png
apprise/assets/themes/default/apprise-failure-72x72.png
apprise/assets/themes/default/apprise-info-128x128.ico
apprise/assets/themes/default/apprise-info-128x128.png
apprise/assets/themes/default/apprise-info-256x256.png
apprise/assets/themes/default/apprise-info-32x32.png
apprise/assets/themes/default/apprise-info-72x72.png
apprise/assets/themes/default/apprise-logo.png
apprise/assets/themes/default/apprise-success-128x128.ico
apprise/assets/themes/default/apprise-success-128x128.png
apprise/assets/themes/default/apprise-success-256x256.png
apprise/assets/themes/default/apprise-success-32x32.png
apprise/assets/themes/default/apprise-success-72x72.png
apprise/assets/themes/default/apprise-warning-128x128.ico
apprise/assets/themes/default/apprise-warning-128x128.png
apprise/assets/themes/default/apprise-warning-256x256.png
apprise/assets/themes/default/apprise-warning-32x32.png
apprise/assets/themes/default/apprise-warning-72x72.png
apprise/attachment/__init__.py
apprise/attachment/base.py
apprise/attachment/file.py
apprise/attachment/http.py
apprise/attachment/memory.py
apprise/config/__init__.py
apprise/config/base.py
apprise/config/file.py
apprise/config/http.py
apprise/config/memory.py
apprise/decorators/__init__.py
apprise/decorators/base.py
apprise/decorators/notify.py
apprise_herbertgao-1.9.6.post1.dist-info/licenses/LICENSE
apprise_herbertgao-1.9.6.post1.dist-info/METADATA
apprise_herbertgao-1.9.6.post1.dist-info/WHEEL
apprise_herbertgao-1.9.6.post1.dist-info/entry_points.txt
apprise_herbertgao-1.9.6.post1.dist-info/top_level.txt
apprise_herbertgao-1.9.6.post1.dist-info/RECORD
