Metadata-Version: 2.4
Name: apprise-herbertgao
Version: 1.9.6.post1
Summary: Push Notifications that work with just about every platform!
Author-email: Herbert Gao <heapcn@gmail.com>
License: BSD-2-Clause
Project-URL: Homepage, https://github.com/HerbertGao/apprise
Project-URL: Source, https://github.com/HerbertGao/apprise
Project-URL: Tracker, https://github.com/HerbertGao/apprise/issues
Project-URL: Documentation, https://github.com/HerbertGao/apprise/wiki
Keywords: 46elks,Africas Talking,Alerts,Apprise API,Automated Packet Reporting System,AWS,Bark,BlueSky,BulkSMS,BulkVS,Burst SMS,Chanify,Chat,CLI,Clickatell,ClickSend,D7Networks,Dapnet,DBus,DingTalk,Discord,Dot,Email,Emby,Enigma2,FCM,Feishu,Flock,Form,Free Mobile,Gnome,Google Chat,Gotify,Growl,Guilded,Home Assistant,httpSMS,IFTTT,Join,JSON,Kavenegar,KODI,Kumulos,LaMetric,Lark,Line,MacOSX,Mailgun,Mastodon,Matrix,Mattermost,MessageBird,Microsoft,Misskey,MQTT,MSG91,MSTeams,Nextcloud,NextcloudTalk,No
Classifier: Development Status :: 5 - Production/Stable
Classifier: Intended Audience :: Developers
Classifier: Intended Audience :: System Administrators
Classifier: Operating System :: OS Independent
Classifier: Natural Language :: English
Classifier: Programming Language :: Python
Classifier: Programming Language :: Python :: 3.9
Classifier: Programming Language :: Python :: 3.10
Classifier: Programming Language :: Python :: 3.11
Classifier: Programming Language :: Python :: 3.12
Classifier: Programming Language :: Python :: Implementation :: CPython
Classifier: Programming Language :: Python :: Implementation :: PyPy
Classifier: Topic :: Software Development :: Libraries :: Python Modules
Classifier: Topic :: Software Development :: Libraries :: Application Frameworks
Requires-Python: >=3.9
License-File: LICENSE
Requires-Dist: requests
Requires-Dist: requests-oauthlib
Requires-Dist: click>=5.0
Requires-Dist: markdown
Requires-Dist: PyYAML
Requires-Dist: certifi
Requires-Dist: tzdata; platform_system == "Windows"
Provides-Extra: dev
Requires-Dist: coverage; extra == "dev"
Requires-Dist: mock; extra == "dev"
Requires-Dist: tox; extra == "dev"
Requires-Dist: pytest; extra == "dev"
Requires-Dist: pytest-cov; extra == "dev"
Requires-Dist: pytest-mock; extra == "dev"
Requires-Dist: ruff; extra == "dev"
Requires-Dist: babel; extra == "dev"
Requires-Dist: validate-pyproject; extra == "dev"
Provides-Extra: all-plugins
Requires-Dist: cryptography; extra == "all-plugins"
Requires-Dist: gntp; extra == "all-plugins"
Requires-Dist: paho-mqtt!=2.0.*; extra == "all-plugins"
Requires-Dist: PGPy; extra == "all-plugins"
Requires-Dist: smpplib; extra == "all-plugins"
Provides-Extra: windows
Requires-Dist: pywin32; extra == "windows"
Requires-Dist: tzdata; extra == "windows"
Dynamic: license-file
